baumbelt/__init__.py
baumbelt/cache.py
baumbelt/enums.py
baumbelt/grouping.py
baumbelt/logs.py
baumbelt/requests.py
baumbelt/timing.py
baumbelt/django/__init__.py
baumbelt/django/s3utils/__init__.py
baumbelt/django/s3utils/apps.py
baumbelt/django/s3utils/storage.py
baumbelt/django/s3utils/utils.py
baumbelt/django/s3utils/management/__init__.py
baumbelt/django/s3utils/management/commands/__init__.py
baumbelt/django/s3utils/management/commands/wait-for-migrations.py
baumbelt/django/sql/__init__.py
baumbelt/django/sql/query_counting.py
baumbelt/django/sql/query_logging.py
baumbelt-1.6.1.dist-info/METADATA
baumbelt-1.6.1.dist-info/WHEEL
baumbelt-1.6.1.dist-info/licenses/LICENSE
baumbelt-1.6.1.dist-info/RECORD
