Metadata-Version: 2.4
Name: baumbelt
Version: 1.6.1
Summary: A collection of Python utility functions by Tenhil GmbH & Co. KG
Project-URL: Homepage, https://github.com/Tenhil-GmbH-Co-KG/baumbelt
Project-URL: Issues, https://github.com/Tenhil-GmbH-Co-KG/baumbelt/issues
Author-email: Watte <python@tenhil.de>
License-File: LICENSE
Classifier: Intended Audience :: Developers
Classifier: License :: OSI Approved :: MIT License
Classifier: Operating System :: OS Independent
Classifier: Programming Language :: Python :: 3
Classifier: Topic :: Software Development
Classifier: Topic :: Utilities
Requires-Python: >=3.11
Requires-Dist: pygments>=2.18.0
Requires-Dist: requests>=2.32.5
Provides-Extra: dev
Requires-Dist: build==1.2.1; extra == 'dev'
Requires-Dist: pytest==8.2.1; extra == 'dev'
Requires-Dist: ruff==0.11.10; extra == 'dev'
Requires-Dist: twine==5.1.0; extra == 'dev'
Provides-Extra: django
Requires-Dist: boto3>=1.37.14; extra == 'django'
Requires-Dist: django-storages>=1.14.5; extra == 'django'
Requires-Dist: django>=5.0.6; extra == 'django'
